aidt/__init__.py
aidt-0.0.1.dist-info/LICENSE
aidt-0.0.1.dist-info/METADATA
aidt-0.0.1.dist-info/WHEEL
aidt-0.0.1.dist-info/RECORD
