Metadata-Version: 2.1
Name: aidt
Version: 0.0.1
Summary: Data transformations using LLMs for use with pandas
License: MIT
Author: Madhav Singhal
Requires-Python: >=3.10,<4.0
Classifier: License :: OSI Approved :: MIT License
Classifier: Programming Language :: Python :: 3
Classifier: Programming Language :: Python :: 3.10
Classifier: Programming Language :: Python :: 3.11
Requires-Dist: openai (>=0.27.0,<0.28.0)
